poetry_docker_plugin/__init__.py
poetry_docker_plugin/docker_builder.py
poetry_docker_plugin/plugin.py
poetry_docker_plugin-0.6.0.dist-info/LICENSE
poetry_docker_plugin-0.6.0.dist-info/METADATA
poetry_docker_plugin-0.6.0.dist-info/WHEEL
poetry_docker_plugin-0.6.0.dist-info/entry_points.txt
poetry_docker_plugin-0.6.0.dist-info/RECORD
