Metadata-Version: 2.3
Name: poetry-docker-plugin
Version: 0.6.0
Summary: A poetry plugin for configure and build docker images.
License: MIT
Keywords: poetry,packaging,docker
Author: Evangelos Michelioudakis
Author-email: vagmcs@gmail.com
Requires-Python: >=3.9
Classifier: Intended Audience :: Developers
Classifier: Intended Audience :: Information Technology
Classifier: Intended Audience :: System Administrators
Classifier: License :: OSI Approved :: MIT License
Classifier: Operating System :: OS Independent
Classifier: Programming Language :: Python
Classifier: Programming Language :: Python :: 3
Classifier: Programming Language :: Python :: 3.9
Classifier: Programming Language :: Python :: 3.10
Classifier: Programming Language :: Python :: 3.11
Classifier: Programming Language :: Python :: 3.12
Classifier: Programming Language :: Python :: 3.13
Classifier: Programming Language :: Python :: 3 :: Only
Classifier: Topic :: Software Development
Classifier: Topic :: Software Development :: Libraries
Classifier: Topic :: Software Development :: Libraries :: Application Frameworks
Classifier: Topic :: Software Development :: Libraries :: Python Modules
Classifier: Topic :: Software Development :: Version Control :: Git
Classifier: Topic :: System :: Archiving :: Packaging
Classifier: Topic :: System :: Installation/Setup
Classifier: Topic :: System :: Software Distribution
Requires-Dist: gitpython (>=3.1.44,<4.0.0)
Requires-Dist: poetry (>=2.0.0,<3.0.0)
Project-URL: Documentation, https://vagmcs.github.io/poetry-docker-plugin
Project-URL: Homepage, https://github.com/vagmcs/python-blueprint
Project-URL: Repository, https://github.com/vagmcs/poetry-docker-plugin
